README.md
setup.cfg
setup.py
dictnavigator/__init__.py
dictnavigator/navigator.py
dictnavigator.egg-info/PKG-INFO
dictnavigator.egg-info/SOURCES.txt
dictnavigator.egg-info/dependency_links.txt
dictnavigator.egg-info/top_level.txt