Metadata-Version: 2.4
Name: dictnavigator
Version: 1.0
Summary: dictnavigator is a tool for working with nested dictionaries in Python. The DictNavigatorKey class allows easy retrieval, updating, and deletion of values by keys at any depth, even inside nested types (tuple, list, dictionary). It also provides a list of all keys at any nesting level. Especially useful for working with JSON data from APIs, simplifying access and modification of needed values.
Home-page: https://gitlab.com/asurnovsurnov/dictnavigetor.git
Author: Aleksei Surnov
Author-email: asurnovsurnov@gmail.com
License: MIT License
Classifier: Programming Language :: Python :: 3
Classifier: Operating System :: OS Independent
Requires-Python: >=3.5.2
Dynamic: author
Dynamic: author-email
Dynamic: classifier
Dynamic: description
Dynamic: description-content-type
Dynamic: home-page
Dynamic: license
Dynamic: requires-python
Dynamic: summary
